AUTHORS
ChangeLog
LICENSE
README.rst
requirements.txt
sample-collectd.conf
sample-graphs-1.png
setup.cfg
setup.py
collectd_swift_stat/__init__.py
collectd_swift_stat.egg-info/PKG-INFO
collectd_swift_stat.egg-info/SOURCES.txt
collectd_swift_stat.egg-info/dependency_links.txt
collectd_swift_stat.egg-info/not-zip-safe
collectd_swift_stat.egg-info/pbr.json
collectd_swift_stat.egg-info/requires.txt
collectd_swift_stat.egg-info/top_level.txt