Metadata-Version: 1.1
Name: collectd-swift-stat
Version: 0.0.2
Summary: Collectd plugin to poll for OpenStack Swift Account.
Home-page: https://github.com/akrzos/collectd-swift-stat
Author: Alex Krzos
Author-email: akrzos@redhat.com
License: Apache-2
Platform: UNKNOWN
Classifier: Development Status :: 5 - Production/Stable
Classifier: Intended Audience :: Developers
Classifier: Intended Audience :: Information Technology
Classifier: Intended Audience :: System Administrators
Classifier: License :: OSI Approved :: Apache Software License
Classifier: Programming Language :: Python
Classifier: Programming Language :: Python :: 2
Classifier: Programming Language :: Python :: 2.7
Classifier: Programming Language :: Python :: 3
Classifier: Programming Language :: Python :: 3.5
Classifier: Topic :: System :: Monitoring
